topsis_padampreet_102303222/__init__.py
topsis_padampreet_102303222/topsis.py
topsis_padampreet_102303222-0.1.1.dist-info/LICENSE
topsis_padampreet_102303222-0.1.1.dist-info/METADATA
topsis_padampreet_102303222-0.1.1.dist-info/WHEEL
topsis_padampreet_102303222-0.1.1.dist-info/entry_points.txt
topsis_padampreet_102303222-0.1.1.dist-info/top_level.txt
topsis_padampreet_102303222-0.1.1.dist-info/RECORD
