Metadata-Version: 2.1
Name: topsis-padampreet-102303222
Version: 0.1.1
Summary: TOPSIS implementation using Python
Home-page: UNKNOWN
Author: Padampreet Singh
Author-email: spadampreet@gmail.com
License: UNKNOWN
Platform: UNKNOWN
Classifier: Programming Language :: Python :: 3
Classifier: License :: OSI Approved :: MIT License
License-File: LICENSE
Requires-Dist: pandas
Requires-Dist: numpy
